[
  {
    "endTime" : "2024-01-02 18:00",
    "podcastName" : "Right to Speak",
    "episodeName" : "SDP INTERLUDE ",
    "msPlayed" : 328330
  },
  {
    "endTime" : "2024-01-02 18:06",
    "podcastName" : "MamonCast",
    "episodeName" : "Drugs You Should Try It -Travis Scott",
    "msPlayed" : 209235
  },
  {
    "endTime" : "2024-01-04 14:45",
    "podcastName" : "MamonCast",
    "episodeName" : "Drugs You Should Try It -Travis Scott",
    "msPlayed" : 209235
  },
  {
    "endTime" : "2024-01-05 18:09",
    "podcastName" : "MamonCast",
    "episodeName" : "Drugs You Should Try It -Travis Scott",
    "msPlayed" : 209235
  },
  {
    "endTime" : "2024-01-12 00:19",
    "podcastName" : "MamonCast",
    "episodeName" : "Drugs You Should Try It -Travis Scott",
    "msPlayed" : 127780
  },
  {
    "endTime" : "2024-01-12 07:46",
    "podcastName" : "Right to Speak",
    "episodeName" : "SDP INTERLUDE ",
    "msPlayed" : 254282
  },
  {
    "endTime" : "2024-01-12 07:49",
    "podcastName" : "MamonCast",
    "episodeName" : "Drugs You Should Try It -Travis Scott",
    "msPlayed" : 82235
  },
  {
    "endTime" : "2024-01-14 07:30",
    "podcastName" : "Right to Speak",
    "episodeName" : "SDP INTERLUDE ",
    "msPlayed" : 74330
  },
  {
    "endTime" : "2024-01-14 07:34",
    "podcastName" : "MamonCast",
    "episodeName" : "Drugs You Should Try It -Travis Scott",
    "msPlayed" : 209235
  },
  {
    "endTime" : "2024-01-14 18:27",
    "podcastName" : "MamonCast",
    "episodeName" : "Drugs You Should Try It -Travis Scott",
    "msPlayed" : 189780
  },
  {
    "endTime" : "2024-01-23 15:03",
    "podcastName" : "MamonCast",
    "episodeName" : "Drugs You Should Try It -Travis Scott",
    "msPlayed" : 198266
  },
  {
    "endTime" : "2024-01-23 15:06",
    "podcastName" : "Right to Speak",
    "episodeName" : "SDP INTERLUDE ",
    "msPlayed" : 35321
  },
  {
    "endTime" : "2024-01-28 15:43",
    "podcastName" : "𝙰𝚛𝚌𝚑𝚒𝚟𝚎𝚜",
    "episodeName" : "H00DBYAIR",
    "msPlayed" : 49197
  },
  {
    "endTime" : "2024-02-11 11:17",
    "podcastName" : "Burdie Stories",
    "episodeName" : "How To Beat Any Addiction...",
    "msPlayed" : 0
  },
  {
    "endTime" : "2024-02-11 11:17",
    "podcastName" : "Burdie Stories",
    "episodeName" : "How To Beat Any Addiction...",
    "msPlayed" : 862
  },
  {
    "endTime" : "2024-02-11 11:53",
    "podcastName" : "MamonCast",
    "episodeName" : "Drugs You Should Try It -Travis Scott",
    "msPlayed" : 16579
  },
  {
    "endTime" : "2024-02-11 11:53",
    "podcastName" : "Slušalica - Penkalin znanstveni podcast",
    "episodeName" : "Adrian Satja Kurdija: Umjetnost umjetne inteligencije -- Slušalica -- Umjetna Inteligencija #1",
    "msPlayed" : 2152142
  },
  {
    "endTime" : "2024-02-11 12:27",
    "podcastName" : "Unreleased ",
    "episodeName" : "2024",
    "msPlayed" : 213853
  },
  {
    "endTime" : "2024-02-11 12:27",
    "podcastName" : "41D3N",
    "episodeName" : "BACKR00MS",
    "msPlayed" : 12920
  },
  {
    "endTime" : "2024-02-11 12:28",
    "podcastName" : "Unreleased ",
    "episodeName" : "2024",
    "msPlayed" : 38817
  },
  {
    "endTime" : "2024-02-11 12:30",
    "podcastName" : "41D3N",
    "episodeName" : "BACKR00MS",
    "msPlayed" : 139663
  },
  {
    "endTime" : "2024-03-01 22:33",
    "podcastName" : "Antarxtica",
    "episodeName" : "24 Songs - Playboi Carti",
    "msPlayed" : 210934
  },
  {
    "endTime" : "2024-03-01 22:33",
    "podcastName" : "Antarxtica",
    "episodeName" : "if looks could kill - destroy lonely (Slowed)",
    "msPlayed" : 4500
  },
  {
    "endTime" : "2024-03-02 12:56",
    "podcastName" : "Antarxtica",
    "episodeName" : "24 Songs - Playboi Carti",
    "msPlayed" : 188293
  },
  {
    "endTime" : "2024-03-02 13:06",
    "podcastName" : "Antarxtica",
    "episodeName" : "7AM - Playboi Carti",
    "msPlayed" : 43860
  },
  {
    "endTime" : "2024-03-20 18:52",
    "podcastName" : "MamonCast",
    "episodeName" : "Drugs You Should Try It -Travis Scott",
    "msPlayed" : 209235
  },
  {
    "endTime" : "2024-03-20 18:55",
    "podcastName" : "Antarxtica",
    "episodeName" : "7AM - Playboi Carti",
    "msPlayed" : 188260
  },
  {
    "endTime" : "2024-04-14 10:54",
    "podcastName" : "In The Groove",
    "episodeName" : "Drake - Drop And Give Me 50 (Kendrick Lamar Diss)",
    "msPlayed" : 26780
  },
  {
    "endTime" : "2024-04-27 11:06",
    "podcastName" : "Antarxtica",
    "episodeName" : "7AM - Playboi Carti",
    "msPlayed" : 890
  },
  {
    "endTime" : "2024-04-27 19:37",
    "podcastName" : "Antarxtica",
    "episodeName" : "7AM - Playboi Carti",
    "msPlayed" : 25291
  },
  {
    "endTime" : "2024-04-30 18:45",
    "podcastName" : "serigathe2nd",
    "episodeName" : "euphoria",
    "msPlayed" : 395808
  },
  {
    "endTime" : "2024-04-30 18:55",
    "podcastName" : "Antarxtica",
    "episodeName" : "R.I.P. - Playboi Carti (Slowed)",
    "msPlayed" : 5100
  },
  {
    "endTime" : "2024-05-01 23:30",
    "podcastName" : "serigathe2nd",
    "episodeName" : "euphoria",
    "msPlayed" : 2020
  },
  {
    "endTime" : "2024-05-05 18:37",
    "podcastName" : "Kendrick Vs Drake",
    "episodeName" : "6:16 in LA - Kendrick Lamar (Drake Diss Track)",
    "msPlayed" : 209161
  },
  {
    "endTime" : "2024-05-05 23:58",
    "podcastName" : "Kendrick Vs Drake",
    "episodeName" : "6:16 in LA - Kendrick Lamar (Drake Diss Track)",
    "msPlayed" : 314704
  },
  {
    "endTime" : "2024-05-06 00:06",
    "podcastName" : "Kendrick Vs Drake",
    "episodeName" : "Family Matters - Drake (Kendrick Diss Track)",
    "msPlayed" : 197767
  },
  {
    "endTime" : "2024-05-06 00:14",
    "podcastName" : "Kendrick Vs Drake",
    "episodeName" : "meet the grahams - Kendrick Lamar (Drake Diss Track)",
    "msPlayed" : 16138
  },
  {
    "endTime" : "2024-05-06 23:42",
    "podcastName" : "Kendrick Vs Drake",
    "episodeName" : "6:16 in LA - Kendrick Lamar (Drake Diss Track)",
    "msPlayed" : 198760
  },
  {
    "endTime" : "2024-05-07 06:04",
    "podcastName" : "Kendrick Vs Drake",
    "episodeName" : "6:16 in LA - Kendrick Lamar (Drake Diss Track)",
    "msPlayed" : 31208
  },
  {
    "endTime" : "2024-05-07 06:08",
    "podcastName" : "Kendrick Vs Drake",
    "episodeName" : "6:16 in LA - Kendrick Lamar (Drake Diss Track)",
    "msPlayed" : 224208
  },
  {
    "endTime" : "2024-05-07 08:31",
    "podcastName" : "serigathe2nd",
    "episodeName" : "THE HEART PART 6",
    "msPlayed" : 325848
  },
  {
    "endTime" : "2024-05-07 11:42",
    "podcastName" : "serigathe2nd",
    "episodeName" : "THE HEART PART 6",
    "msPlayed" : 287320
  },
  {
    "endTime" : "2024-05-07 12:00",
    "podcastName" : "Kendrick Vs Drake",
    "episodeName" : "6:16 in LA - Kendrick Lamar (Drake Diss Track)",
    "msPlayed" : 216048
  },
  {
    "endTime" : "2024-05-07 15:58",
    "podcastName" : "serigathe2nd",
    "episodeName" : "THE HEART PART 6",
    "msPlayed" : 6300
  },
  {
    "endTime" : "2024-05-07 17:06",
    "podcastName" : "Kendrick Vs Drake",
    "episodeName" : "6:16 in LA - Kendrick Lamar (Drake Diss Track)",
    "msPlayed" : 224208
  },
  {
    "endTime" : "2024-05-07 17:25",
    "podcastName" : "serigathe2nd",
    "episodeName" : "THE HEART PART 6",
    "msPlayed" : 32848
  },
  {
    "endTime" : "2024-05-07 22:04",
    "podcastName" : "serigathe2nd",
    "episodeName" : "THE HEART PART 6",
    "msPlayed" : 470
  },
  {
    "endTime" : "2024-05-07 23:20",
    "podcastName" : "serigathe2nd",
    "episodeName" : "THE HEART PART 6",
    "msPlayed" : 325848
  },
  {
    "endTime" : "2024-05-09 21:17",
    "podcastName" : "NFR Podcast",
    "episodeName" : "Top 10 AUX Songs of All-Time",
    "msPlayed" : 16490
  },
  {
    "endTime" : "2024-05-10 00:18",
    "podcastName" : "Bits of Infinity ",
    "episodeName" : "6:16 in Los Angeles (Drake Diss)",
    "msPlayed" : 22330
  },
  {
    "endTime" : "2024-05-11 12:42",
    "podcastName" : "Bits of Infinity ",
    "episodeName" : "6:16 in Los Angeles (Drake Diss)",
    "msPlayed" : 227088
  },
  {
    "endTime" : "2024-05-11 13:06",
    "podcastName" : "Cxll.",
    "episodeName" : "THE HEART PART 6",
    "msPlayed" : 328660
  },
  {
    "endTime" : "2024-05-11 13:06",
    "podcastName" : "Cxll.",
    "episodeName" : "Say It (Hold Up)",
    "msPlayed" : 967
  },
  {
    "endTime" : "2024-05-12 14:05",
    "podcastName" : "Bits of Infinity ",
    "episodeName" : "6:16 in Los Angeles (Drake Diss)",
    "msPlayed" : 242568
  },
  {
    "endTime" : "2024-05-12 14:29",
    "podcastName" : "1x4uuman",
    "episodeName" : "The Heart Part 6",
    "msPlayed" : 300212
  },
  {
    "endTime" : "2024-05-12 23:49",
    "podcastName" : "Dissect",
    "episodeName" : "S1E9 - Alright by Kendrick Lamar",
    "msPlayed" : 0
  },
  {
    "endTime" : "2024-05-12 23:50",
    "podcastName" : "Dissect",
    "episodeName" : " BONUS - Mid-Season Recap w/ Cole & Femi",
    "msPlayed" : 13669
  },
  {
    "endTime" : "2024-05-12 23:50",
    "podcastName" : "Dissect",
    "episodeName" : "S1E10 - For Sale? by Kendrick Lamar",
    "msPlayed" : 3887
  },
  {
    "endTime" : "2024-05-13 00:11",
    "podcastName" : "Dissect",
    "episodeName" : "S5E10 - PRIDE. by Kendrick Lamar",
    "msPlayed" : 1137440
  },
  {
    "endTime" : "2024-05-13 16:11",
    "podcastName" : "1x4uuman",
    "episodeName" : "The Heart Part 6",
    "msPlayed" : 294909
  },
  {
    "endTime" : "2024-05-17 19:24",
    "podcastName" : "Bits of Infinity ",
    "episodeName" : "6:16 in Los Angeles (Drake Diss)",
    "msPlayed" : 5390
  },
  {
    "endTime" : "2024-05-17 19:24",
    "podcastName" : "Bits of Infinity ",
    "episodeName" : "6:16 in Los Angeles (Drake Diss)",
    "msPlayed" : 228364
  },
  {
    "endTime" : "2024-05-17 19:25",
    "podcastName" : "Bits of Infinity ",
    "episodeName" : "6:16 in Los Angeles (Drake Diss)",
    "msPlayed" : 9420
  },
  {
    "endTime" : "2024-05-17 19:44",
    "podcastName" : "1x4uuman",
    "episodeName" : "The Heart Part 6",
    "msPlayed" : 39215
  },
  {
    "endTime" : "2024-05-17 19:48",
    "podcastName" : "1x4uuman",
    "episodeName" : "The Heart Part 6",
    "msPlayed" : 240084
  },
  {
    "endTime" : "2024-05-18 16:58",
    "podcastName" : "Bits of Infinity ",
    "episodeName" : "6:16 in Los Angeles (Drake Diss)",
    "msPlayed" : 181938
  },
  {
    "endTime" : "2024-05-21 09:22",
    "podcastName" : "Bits of Infinity ",
    "episodeName" : "6:16 in Los Angeles (Drake Diss)",
    "msPlayed" : 224815
  },
  {
    "endTime" : "2024-05-21 10:28",
    "podcastName" : "1x4uuman",
    "episodeName" : "The Heart Part 6",
    "msPlayed" : 17699
  },
  {
    "endTime" : "2024-05-22 14:17",
    "podcastName" : "Bits of Infinity ",
    "episodeName" : "6:16 in Los Angeles (Drake Diss)",
    "msPlayed" : 224815
  },
  {
    "endTime" : "2024-05-22 14:41",
    "podcastName" : "1x4uuman",
    "episodeName" : "The Heart Part 6",
    "msPlayed" : 308855
  },
  {
    "endTime" : "2024-05-23 09:50",
    "podcastName" : "MamonCast",
    "episodeName" : "Drugs You Should Try It -Travis Scott",
    "msPlayed" : 127160
  },
  {
    "endTime" : "2024-05-23 13:36",
    "podcastName" : "MamonCast",
    "episodeName" : "Drugs You Should Try It -Travis Scott",
    "msPlayed" : 91235
  },
  {
    "endTime" : "2024-05-23 13:41",
    "podcastName" : "Right to Speak",
    "episodeName" : "SDP INTERLUDE ",
    "msPlayed" : 328331
  },
  {
    "endTime" : "2024-05-23 13:45",
    "podcastName" : "Antarxtica",
    "episodeName" : "7AM - Playboi Carti",
    "msPlayed" : 217260
  },
  {
    "endTime" : "2024-05-29 10:13",
    "podcastName" : "Bits of Infinity ",
    "episodeName" : "6:16 in Los Angeles (Drake Diss)",
    "msPlayed" : 224815
  },
  {
    "endTime" : "2024-06-03 13:29",
    "podcastName" : "Bits of Infinity ",
    "episodeName" : "6:16 in Los Angeles (Drake Diss)",
    "msPlayed" : 224815
  },
  {
    "endTime" : "2024-06-12 19:38",
    "podcastName" : "Antarxtica",
    "episodeName" : "7AM - Playboi Carti",
    "msPlayed" : 217260
  },
  {
    "endTime" : "2024-06-12 19:44",
    "podcastName" : "Right to Speak",
    "episodeName" : "SDP INTERLUDE ",
    "msPlayed" : 328330
  },
  {
    "endTime" : "2024-06-12 19:47",
    "podcastName" : "Antarxtica",
    "episodeName" : "24 Songs - Playboi Carti",
    "msPlayed" : 225906
  },
  {
    "endTime" : "2024-06-12 19:51",
    "podcastName" : "MamonCast",
    "episodeName" : "Drugs You Should Try It -Travis Scott",
    "msPlayed" : 209235
  },
  {
    "endTime" : "2024-06-17 14:46",
    "podcastName" : "KENDRICK LAMAR 6:16 IN LA",
    "episodeName" : "KENDRICK LAMAR - 6:16 IN LA",
    "msPlayed" : 7605
  },
  {
    "endTime" : "2024-08-08 22:33",
    "podcastName" : "Right to Speak",
    "episodeName" : "SDP INTERLUDE ",
    "msPlayed" : 7100
  },
  {
    "endTime" : "2024-08-08 22:40",
    "podcastName" : "Thecoolguy72",
    "episodeName" : "Whole lotta red",
    "msPlayed" : 6980
  },
  {
    "endTime" : "2024-08-15 00:12",
    "podcastName" : "Jaedo 's Podcast",
    "episodeName" : "City in the sky",
    "msPlayed" : 9330
  },
  {
    "endTime" : "2024-08-15 00:13",
    "podcastName" : "Thecoolguy72",
    "episodeName" : "Skeleton-carti",
    "msPlayed" : 3430
  },
  {
    "endTime" : "2024-08-15 00:13",
    "podcastName" : "euls",
    "episodeName" : "Skeleton OG",
    "msPlayed" : 15630
  },
  {
    "endTime" : "2024-08-15 00:13",
    "podcastName" : "YeLover939",
    "episodeName" : "Skeletons",
    "msPlayed" : 21440
  },
  {
    "endTime" : "2024-08-15 00:22",
    "podcastName" : "Wait I’m goated",
    "episodeName" : "SKELTONS EXTENDED",
    "msPlayed" : 9660
  },
  {
    "endTime" : "2024-08-17 12:51",
    "podcastName" : "S ",
    "episodeName" : "molly - playboi carti",
    "msPlayed" : 2843
  },
  {
    "endTime" : "2024-08-17 21:29",
    "podcastName" : "euls",
    "episodeName" : "Skeleton OG",
    "msPlayed" : 95280
  },
  {
    "endTime" : "2024-08-17 21:30",
    "podcastName" : "euls",
    "episodeName" : "Skeleton OG",
    "msPlayed" : 11270
  },
  {
    "endTime" : "2024-08-17 21:30",
    "podcastName" : "YeLover939",
    "episodeName" : "Skeletons",
    "msPlayed" : 64420
  },
  {
    "endTime" : "2024-08-17 21:35",
    "podcastName" : "Jaedo 's Podcast",
    "episodeName" : "City in the sky",
    "msPlayed" : 328815
  },
  {
    "endTime" : "2024-08-17 21:37",
    "podcastName" : "Thecoolguy72",
    "episodeName" : "Whole lotta red",
    "msPlayed" : 120575
  },
  {
    "endTime" : "2024-08-17 21:40",
    "podcastName" : "S ",
    "episodeName" : "molly - playboi carti",
    "msPlayed" : 158127
  },
  {
    "endTime" : "2024-08-17 21:43",
    "podcastName" : "Thecoolguy72",
    "episodeName" : "Skeleton-carti",
    "msPlayed" : 183027
  },
  {
    "endTime" : "2024-08-17 21:47",
    "podcastName" : "Antarxtica",
    "episodeName" : "24 Songs - Playboi Carti",
    "msPlayed" : 225906
  },
  {
    "endTime" : "2024-08-17 21:51",
    "podcastName" : "Antarxtica",
    "episodeName" : "7AM - Playboi Carti",
    "msPlayed" : 217260
  },
  {
    "endTime" : "2024-08-17 21:56",
    "podcastName" : "Right to Speak",
    "episodeName" : "SDP INTERLUDE ",
    "msPlayed" : 328330
  },
  {
    "endTime" : "2024-08-17 21:59",
    "podcastName" : "MamonCast",
    "episodeName" : "Drugs You Should Try It -Travis Scott",
    "msPlayed" : 209235
  },
  {
    "endTime" : "2024-08-17 22:03",
    "podcastName" : "MamonCast",
    "episodeName" : "Kanye West - Mama's Boyfriend",
    "msPlayed" : 224332
  },
  {
    "endTime" : "2024-08-19 14:48",
    "podcastName" : "Jaedo 's Podcast",
    "episodeName" : "City in the sky",
    "msPlayed" : 321985
  },
  {
    "endTime" : "2024-08-19 14:50",
    "podcastName" : "Thecoolguy72",
    "episodeName" : "Whole lotta red",
    "msPlayed" : 120575
  },
  {
    "endTime" : "2024-08-19 14:53",
    "podcastName" : "S ",
    "episodeName" : "molly - playboi carti",
    "msPlayed" : 158127
  },
  {
    "endTime" : "2024-08-19 14:56",
    "podcastName" : "Thecoolguy72",
    "episodeName" : "Skeleton-carti",
    "msPlayed" : 183027
  },
  {
    "endTime" : "2024-08-19 15:00",
    "podcastName" : "Antarxtica",
    "episodeName" : "24 Songs - Playboi Carti",
    "msPlayed" : 225906
  },
  {
    "endTime" : "2024-08-19 15:04",
    "podcastName" : "Antarxtica",
    "episodeName" : "7AM - Playboi Carti",
    "msPlayed" : 217260
  },
  {
    "endTime" : "2024-08-19 15:09",
    "podcastName" : "Right to Speak",
    "episodeName" : "SDP INTERLUDE ",
    "msPlayed" : 328330
  },
  {
    "endTime" : "2024-08-19 15:13",
    "podcastName" : "MamonCast",
    "episodeName" : "Drugs You Should Try It -Travis Scott",
    "msPlayed" : 209235
  },
  {
    "endTime" : "2024-08-20 14:34",
    "podcastName" : "Jaedo 's Podcast",
    "episodeName" : "City in the sky",
    "msPlayed" : 321985
  },
  {
    "endTime" : "2024-08-20 14:46",
    "podcastName" : "Thecoolguy72",
    "episodeName" : "Whole lotta red",
    "msPlayed" : 120575
  },
  {
    "endTime" : "2024-08-20 14:49",
    "podcastName" : "S ",
    "episodeName" : "molly - playboi carti",
    "msPlayed" : 158127
  },
  {
    "endTime" : "2024-08-20 14:52",
    "podcastName" : "Thecoolguy72",
    "episodeName" : "Skeleton-carti",
    "msPlayed" : 183027
  },
  {
    "endTime" : "2024-08-20 14:56",
    "podcastName" : "Antarxtica",
    "episodeName" : "24 Songs - Playboi Carti",
    "msPlayed" : 225906
  },
  {
    "endTime" : "2024-08-20 14:59",
    "podcastName" : "Antarxtica",
    "episodeName" : "7AM - Playboi Carti",
    "msPlayed" : 217260
  },
  {
    "endTime" : "2024-08-20 15:05",
    "podcastName" : "Right to Speak",
    "episodeName" : "SDP INTERLUDE ",
    "msPlayed" : 328330
  },
  {
    "endTime" : "2024-08-20 15:08",
    "podcastName" : "MamonCast",
    "episodeName" : "Drugs You Should Try It -Travis Scott",
    "msPlayed" : 209235
  },
  {
    "endTime" : "2024-08-20 15:17",
    "podcastName" : "Jaedo 's Podcast",
    "episodeName" : "Life of the party ( Both Ye verses )",
    "msPlayed" : 531069
  },
  {
    "endTime" : "2024-08-20 15:23",
    "podcastName" : "MamonCast",
    "episodeName" : "Capitulo Especial. Que prefieres?",
    "msPlayed" : 326420
  },
  {
    "endTime" : "2024-08-26 20:25",
    "podcastName" : "Jaedo 's Podcast",
    "episodeName" : "City in the sky",
    "msPlayed" : 169460
  },
  {
    "endTime" : "2024-08-26 20:27",
    "podcastName" : "Thecoolguy72",
    "episodeName" : "Whole lotta red",
    "msPlayed" : 120575
  },
  {
    "endTime" : "2024-08-26 20:30",
    "podcastName" : "Thecoolguy72",
    "episodeName" : "Skeleton-carti",
    "msPlayed" : 183027
  },
  {
    "endTime" : "2024-08-26 20:36",
    "podcastName" : "Right to Speak",
    "episodeName" : "SDP INTERLUDE ",
    "msPlayed" : 328330
  },
  {
    "endTime" : "2024-08-26 20:39",
    "podcastName" : "MamonCast",
    "episodeName" : "Drugs You Should Try It -Travis Scott",
    "msPlayed" : 209235
  },
  {
    "endTime" : "2024-10-28 11:55",
    "podcastName" : "Bits of Infinity ",
    "episodeName" : "6:16 in Los Angeles (Drake Diss)",
    "msPlayed" : 224815
  },
  {
    "endTime" : "2024-10-28 12:20",
    "podcastName" : "yad._wlr ",
    "episodeName" : "The Heart Part 6 (Drake)",
    "msPlayed" : 258461
  },
  {
    "endTime" : "2024-11-09 14:15",
    "podcastName" : "Bits of Infinity ",
    "episodeName" : "6:16 in Los Angeles (Drake Diss)",
    "msPlayed" : 224815
  },
  {
    "endTime" : "2024-11-09 14:39",
    "podcastName" : "yad._wlr ",
    "episodeName" : "The Heart Part 6 (Drake)",
    "msPlayed" : 341337
  },
  {
    "endTime" : "2024-11-14 01:11",
    "podcastName" : "LOOD ",
    "episodeName" : "#121 Snaga Intuicije u donošenju odlkuka: Janja Benić Janjolinka",
    "msPlayed" : 2442
  },
  {
    "endTime" : "2024-11-15 20:00",
    "podcastName" : "LOOD ",
    "episodeName" : "#121 Snaga Intuicije u donošenju odlkuka: Janja Benić Janjolinka",
    "msPlayed" : 0
  },
  {
    "endTime" : "2024-11-16 10:49",
    "podcastName" : "LOOD ",
    "episodeName" : "#121 Snaga Intuicije u donošenju odlkuka: Janja Benić Janjolinka",
    "msPlayed" : 3614
  },
  {
    "endTime" : "2024-11-21 21:54",
    "podcastName" : "dontha16",
    "episodeName" : "Hate Me - Lil Yachty & ian",
    "msPlayed" : 14564
  },
  {
    "endTime" : "2024-11-21 21:54",
    "podcastName" : "dontha16",
    "episodeName" : "The Prayer - Kendrick Lamar",
    "msPlayed" : 328404
  },
  {
    "endTime" : "2024-11-21 22:05",
    "podcastName" : "Jaedo 's Podcast",
    "episodeName" : "City in the sky",
    "msPlayed" : 26478
  },
  {
    "endTime" : "2024-11-21 23:11",
    "podcastName" : "dontha16",
    "episodeName" : "The Prayer - Kendrick Lamar",
    "msPlayed" : 90720
  },
  {
    "endTime" : "2024-11-21 23:21",
    "podcastName" : "dontha16",
    "episodeName" : "The Prayer - Kendrick Lamar",
    "msPlayed" : 316491
  },
  {
    "endTime" : "2024-11-21 23:39",
    "podcastName" : "dontha16",
    "episodeName" : "The Prayer - Kendrick Lamar",
    "msPlayed" : 323780
  },
  {
    "endTime" : "2024-11-22 11:15",
    "podcastName" : "dontha16",
    "episodeName" : "The Prayer - Kendrick Lamar",
    "msPlayed" : 207980
  },
  {
    "endTime" : "2024-11-22 13:28",
    "podcastName" : "dontha16",
    "episodeName" : "The Prayer - Kendrick Lamar",
    "msPlayed" : 322455
  },
  {
    "endTime" : "2024-11-23 13:53",
    "podcastName" : "dontha16",
    "episodeName" : "The Prayer - Kendrick Lamar",
    "msPlayed" : 117360
  },
  {
    "endTime" : "2024-11-23 15:29",
    "podcastName" : "dontha16",
    "episodeName" : "The Prayer - Kendrick Lamar",
    "msPlayed" : 323631
  },
  {
    "endTime" : "2024-11-24 09:41",
    "podcastName" : "dontha16",
    "episodeName" : "The Prayer - Kendrick Lamar",
    "msPlayed" : 143220
  },
  {
    "endTime" : "2024-11-24 12:31",
    "podcastName" : "dontha16",
    "episodeName" : "The Prayer - Kendrick Lamar",
    "msPlayed" : 132800
  },
  {
    "endTime" : "2024-11-26 02:27",
    "podcastName" : "AntonyWest911",
    "episodeName" : "Prayer",
    "msPlayed" : 200646
  },
  {
    "endTime" : "2024-11-26 02:31",
    "podcastName" : "AntonyWest911",
    "episodeName" : "Prayer",
    "msPlayed" : 143137
  },
  {
    "endTime" : "2024-11-26 10:24",
    "podcastName" : "AntonyWest911",
    "episodeName" : "Prayer",
    "msPlayed" : 4872
  },
  {
    "endTime" : "2024-11-26 18:20",
    "podcastName" : "AntonyWest911",
    "episodeName" : "Prayer",
    "msPlayed" : 171938
  },
  {
    "endTime" : "2024-11-30 14:39",
    "podcastName" : "AntonyWest911",
    "episodeName" : "sdp interlude (Extended)",
    "msPlayed" : 5255
  },
  {
    "endTime" : "2024-11-30 14:39",
    "podcastName" : "The Podcast With Soul",
    "episodeName" : "DON'T GET DISCOURAGED || BELIEVE THAT YOU CAN",
    "msPlayed" : 153
  },
  {
    "endTime" : "2024-11-30 19:57",
    "podcastName" : "AntonyWest911",
    "episodeName" : "sdp interlude (Extended)",
    "msPlayed" : 1221
  },
  {
    "endTime" : "2024-11-30 20:23",
    "podcastName" : "AntonyWest911",
    "episodeName" : "Prayer",
    "msPlayed" : 608822
  },
  {
    "endTime" : "2024-11-30 20:35",
    "podcastName" : "Jaedo 's Podcast",
    "episodeName" : "City in the sky",
    "msPlayed" : 119587
  },
  {
    "endTime" : "2024-11-30 21:29",
    "podcastName" : "AntonyWest911",
    "episodeName" : "Prayer",
    "msPlayed" : 321012
  },
  {
    "endTime" : "2024-11-30 21:29",
    "podcastName" : "Jaedo 's Podcast",
    "episodeName" : "City in the sky",
    "msPlayed" : 6387
  },
  {
    "endTime" : "2024-11-30 22:18",
    "podcastName" : "AntonyWest911",
    "episodeName" : "sdp interlude (Extended)",
    "msPlayed" : 6610
  },
  {
    "endTime" : "2024-11-30 22:23",
    "podcastName" : "AntonyWest911",
    "episodeName" : "Prayer",
    "msPlayed" : 321012
  },
  {
    "endTime" : "2024-11-30 22:47",
    "podcastName" : "Jaedo 's Podcast",
    "episodeName" : "City in the sky",
    "msPlayed" : 1536
  },
  {
    "endTime" : "2024-12-01 11:11",
    "podcastName" : "AntonyWest911",
    "episodeName" : "Prayer",
    "msPlayed" : 321012
  },
  {
    "endTime" : "2024-12-01 11:11",
    "podcastName" : "Jaedo 's Podcast",
    "episodeName" : "City in the sky",
    "msPlayed" : 16186
  },
  {
    "endTime" : "2024-12-01 19:54",
    "podcastName" : "AntonyWest911",
    "episodeName" : "Prayer",
    "msPlayed" : 241018
  },
  {
    "endTime" : "2024-12-08 06:39",
    "podcastName" : "AntonyWest911",
    "episodeName" : "Prayer",
    "msPlayed" : 1227
  },
  {
    "endTime" : "2024-12-08 06:39",
    "podcastName" : "Jaedo 's Podcast",
    "episodeName" : "City in the sky",
    "msPlayed" : 662
  },
  {
    "endTime" : "2024-12-08 06:39",
    "podcastName" : "AntonyWest911",
    "episodeName" : "sdp interlude (Extended)",
    "msPlayed" : 640
  },
  {
    "endTime" : "2024-12-08 06:44",
    "podcastName" : "AntonyWest911",
    "episodeName" : "Prayer",
    "msPlayed" : 321829
  },
  {
    "endTime" : "2024-12-08 08:24",
    "podcastName" : "Jaedo 's Podcast",
    "episodeName" : "City in the sky",
    "msPlayed" : 23627
  },
  {
    "endTime" : "2024-12-09 22:52",
    "podcastName" : "AntonyWest911",
    "episodeName" : "Prayer",
    "msPlayed" : 58135
  },
  {
    "endTime" : "2024-12-14 14:47",
    "podcastName" : "AntonyWest911",
    "episodeName" : "Prayer",
    "msPlayed" : 352272
  },
  {
    "endTime" : "2024-12-15 07:01",
    "podcastName" : "Jaedo 's Podcast",
    "episodeName" : "City in the sky",
    "msPlayed" : 9066
  },
  {
    "endTime" : "2024-12-15 07:18",
    "podcastName" : "AntonyWest911",
    "episodeName" : "Prayer",
    "msPlayed" : 321012
  },
  {
    "endTime" : "2024-12-15 07:20",
    "podcastName" : "Thecoolguy72",
    "episodeName" : "Whole lotta red",
    "msPlayed" : 89753
  },
  {
    "endTime" : "2024-12-15 17:44",
    "podcastName" : "AntonyWest911",
    "episodeName" : "sdp interlude (Extended)",
    "msPlayed" : 329557
  },
  {
    "endTime" : "2024-12-15 17:50",
    "podcastName" : "AntonyWest911",
    "episodeName" : "Prayer",
    "msPlayed" : 321012
  },
  {
    "endTime" : "2024-12-15 17:55",
    "podcastName" : "Jaedo 's Podcast",
    "episodeName" : "City in the sky",
    "msPlayed" : 321985
  },
  {
    "endTime" : "2024-12-17 14:32",
    "podcastName" : "Phat Ho",
    "episodeName" : "The Heart Part 6 - Drake",
    "msPlayed" : 192363
  },
  {
    "endTime" : "2024-12-19 13:45",
    "podcastName" : "AntonyWest911",
    "episodeName" : "Prayer",
    "msPlayed" : 381041
  },
  {
    "endTime" : "2024-12-19 15:45",
    "podcastName" : "Bits of Infinity ",
    "episodeName" : "6:16 in Los Angeles (Drake Diss)",
    "msPlayed" : 224815
  },
  {
    "endTime" : "2024-12-19 18:31",
    "podcastName" : "AntonyWest911",
    "episodeName" : "Prayer",
    "msPlayed" : 331573
  },
  {
    "endTime" : "2024-12-19 22:08",
    "podcastName" : "AntonyWest911",
    "episodeName" : "Prayer",
    "msPlayed" : 660
  },
  {
    "endTime" : "2024-12-19 22:30",
    "podcastName" : "AntonyWest911",
    "episodeName" : "Prayer",
    "msPlayed" : 53303
  },
  {
    "endTime" : "2024-12-19 22:31",
    "podcastName" : "AntonyWest911",
    "episodeName" : "sdp interlude (Extended)",
    "msPlayed" : 34697
  },
  {
    "endTime" : "2024-12-19 22:35",
    "podcastName" : "AntonyWest911",
    "episodeName" : "Prayer",
    "msPlayed" : 268012
  },
  {
    "endTime" : "2024-12-19 22:41",
    "podcastName" : "AntonyWest911",
    "episodeName" : "sdp interlude (Extended)",
    "msPlayed" : 328332
  }
]